{"transport_mode":"TRAIN","length":19,"width":2,"door_max":11,"parts":[{"name":"loco_ext","stage":"EXTERIOR","mirror":false,"skip_rendering_if_too_far":false,"door_offset":"NONE","render_condition":"ALL","positions":[[0.0,0.0]],"whitelisted_cars":"1","blacklisted_cars":"%1"},{"name":"loco_int","stage":"INTERIOR","mirror":false,"skip_rendering_if_too_far":false,"door_offset":"NONE","render_condition":"ALL","positions":[[0.0,0.0]],"whitelisted_cars":"1","blacklisted_cars":"%1"},{"name":"headlights","stage":"ALWAYS_ON_LIGHTS","mirror":true,"skip_rendering_if_too_far":false,"door_offset":"NONE","render_condition":"MOVING_FORWARDS","positions":[[0.0,0.0]],"whitelisted_cars":"1","blacklisted_cars":"%1"},{"name":"taillights","stage":"ALWAYS_ON_LIGHTS","mirror":true,"skip_rendering_if_too_far":false,"door_offset":"NONE","render_condition":"MOVING_BACKWARDS","positions":[[0.0,0.0]],"whitelisted_cars":"1","blacklisted_cars":"%1"},{"name":"coach_ext","stage":"EXTERIOR","mirror":false,"skip_rendering_if_too_far":false,"door_offset":"NONE","render_condition":"ALL","positions":[[0.0,0.0]],"whitelisted_cars":"","blacklisted_cars":"1,-1"},{"name":"coach_int","stage":"INTERIOR","mirror":false,"skip_rendering_if_too_far":false,"door_offset":"NONE","render_condition":"ALL","positions":[[0.0,0.0]],"whitelisted_cars":"","blacklisted_cars":"1,-1"},{"name":"cabcar_ext","stage":"EXTERIOR","mirror":true,"skip_rendering_if_too_far":false,"door_offset":"NONE","render_condition":"ALL","positions":[[0.0,0.0]],"whitelisted_cars":"-1","blacklisted_cars":"%1"},{"name":"cabcar_int","stage":"INTERIOR","mirror":true,"skip_rendering_if_too_far":false,"door_offset":"NONE","render_condition":"ALL","positions":[[0.0,0.0]],"whitelisted_cars":"-1","blacklisted_cars":"%1"},{"name":"cabcar_headlight","stage":"ALWAYS_ON_LIGHTS","mirror":true,"skip_rendering_if_too_far":false,"door_offset":"NONE","render_condition":"MOVING_BACKWARDS","positions":[[0.0,0.0]],"whitelisted_cars":"-1","blacklisted_cars":"%1"},{"name":"cabcar_taillight","stage":"ALWAYS_ON_LIGHTS","mirror":true,"skip_rendering_if_too_far":false,"door_offset":"NONE","render_condition":"MOVING_FORWARDS","positions":[[0.0,0.0]],"whitelisted_cars":"-1","blacklisted_cars":"%1"},{"name":"coach_light","stage":"LIGHTS","mirror":false,"skip_rendering_if_too_far":false,"door_offset":"NONE","render_condition":"ALL","positions":[[0.0,0.0]],"whitelisted_cars":"","blacklisted_cars":"1"},{"name":"bogie","stage":"EXTERIOR","mirror":false,"skip_rendering_if_too_far":false,"door_offset":"NONE","render_condition":"ALL","positions":[[0.0,100.0],[0.0,-100.0]],"whitelisted_cars":"","blacklisted_cars":""},{"name":"door_ext","stage":"EXTERIOR","mirror":false,"skip_rendering_if_too_far":false,"door_offset":"RIGHT_NEGATIVE","render_condition":"ALL","positions":[[0.0,144.0]],"whitelisted_cars":"","blacklisted_cars":"1"},{"name":"door_int","stage":"INTERIOR","mirror":false,"skip_rendering_if_too_far":false,"door_offset":"RIGHT_NEGATIVE","render_condition":"ALL","positions":[[0.0,144.0]],"whitelisted_cars":"","blacklisted_cars":"1"},{"name":"door_ext","stage":"EXTERIOR","mirror":false,"skip_rendering_if_too_far":false,"door_offset":"RIGHT_POSITIVE","render_condition":"ALL","positions":[[0.0,-144.0]],"whitelisted_cars":"","blacklisted_cars":"1"},{"name":"door_int","stage":"INTERIOR","mirror":false,"skip_rendering_if_too_far":false,"door_offset":"RIGHT_POSITIVE","render_condition":"ALL","positions":[[0.0,-144.0]],"whitelisted_cars":"","blacklisted_cars":"1"},{"name":"door_ext","stage":"EXTERIOR","mirror":true,"skip_rendering_if_too_far":false,"door_offset":"LEFT_POSITIVE","render_condition":"ALL","positions":[[0.0,144.0]],"whitelisted_cars":"","blacklisted_cars":"1,-1"},{"name":"door_int","stage":"INTERIOR","mirror":true,"skip_rendering_if_too_far":false,"door_offset":"LEFT_POSITIVE","render_condition":"ALL","positions":[[0.0,144.0]],"whitelisted_cars":"","blacklisted_cars":"1,-1"},{"name":"door_ext","stage":"EXTERIOR","mirror":true,"skip_rendering_if_too_far":false,"door_offset":"LEFT_NEGATIVE","render_condition":"ALL","positions":[[0.0,-144.0]],"whitelisted_cars":"","blacklisted_cars":"1"},{"name":"door_int","stage":"EXTERIOR","mirror":true,"skip_rendering_if_too_far":false,"door_offset":"LEFT_NEGATIVE","render_condition":"ALL","positions":[[0.0,-144.0]],"whitelisted_cars":"","blacklisted_cars":"1"}]}